setup.py
bastion_proxy/__init__.py
bastion_proxy/__main__.py
bastion_proxy.egg-info/PKG-INFO
bastion_proxy.egg-info/SOURCES.txt
bastion_proxy.egg-info/dependency_links.txt
bastion_proxy.egg-info/entry_points.txt
bastion_proxy.egg-info/requires.txt
bastion_proxy.egg-info/top_level.txt