Metadata-Version: 1.0
Name: bastion-proxy
Version: 1.1.0
Summary: Bastion proxy to connect to other proxies via it.
Home-page: https://github.com/nailgun/bastion-proxy
Author: Nailgun
Author-email: dbashkatov@gmail.com
License: MIT
Platform: UNKNOWN
